dewi_dataclass/__init__.py
dewi_dataclass/node.py
dewi_dataclass-1.0.0.dist-info/COPYING
dewi_dataclass-1.0.0.dist-info/METADATA
dewi_dataclass-1.0.0.dist-info/WHEEL
dewi_dataclass-1.0.0.dist-info/top_level.txt
dewi_dataclass-1.0.0.dist-info/zip-safe
dewi_dataclass-1.0.0.dist-info/RECORD
